pytomosaic/__init__.py
pytomosaic/imageDownloader.py
pytomosaic/mosaic.py
pytomosaic/tileManager.py
pytomosaic-0.1.12.post3.dist-info/licenses/LICENSE
pytomosaic-0.1.12.post3.dist-info/METADATA
pytomosaic-0.1.12.post3.dist-info/WHEEL
pytomosaic-0.1.12.post3.dist-info/top_level.txt
pytomosaic-0.1.12.post3.dist-info/RECORD
