Metadata-Version: 2.4
Name: pytomosaic
Version: 0.1.12.post3
Summary: An Open Source Python library for creating photomosaics
Home-page: https://github.com/RustyLegacy01/Pytomosaic
Author: Luca Noble
Author-email: luca@nofa.uk
Classifier: Programming Language :: Python :: 3
Classifier: License :: OSI Approved :: GNU General Public License v3 (GPLv3)
Classifier: Operating System :: OS Independent
Requires-Python: >=3.10
License-File: LICENSE
Requires-Dist: tqdm
Requires-Dist: numpy
Requires-Dist: Pillow
Dynamic: license-file
